MANIFEST.in
README.rst
setup.cfg
setup.py
django_trackable.egg-info/PKG-INFO
django_trackable.egg-info/SOURCES.txt
django_trackable.egg-info/dependency_links.txt
django_trackable.egg-info/requires.txt
django_trackable.egg-info/top_level.txt
trackable/__init__.py
trackable/admin.py
trackable/exceptions.py
trackable/models.py
trackable/settings.py
trackable/sites.py
trackable/views.py
trackable/contrib/__init__.py
trackable/contrib/celery_tasks.py
trackable/fixtures/spider.json
trackable/management/__init__.py
trackable/management/commands/__init__.py
trackable/management/commands/convert_tracking_data.py
trackable/management/commands/fold_trackable_messages.py
trackable/management/commands/generate_csv.py
trackable/message/__init__.py
trackable/message/counting.py
trackable/message/utils.py
trackable/message/backends/__init__.py
trackable/message/backends/base.py
trackable/message/backends/kombu/__init__.py
trackable/message/backends/kombu/base.py
trackable/tests/__init__.py
trackable/tests/models.py
trackable/tests/trackabledata.py
trackable/tests/urls.py
trackable/tests/views.py
trackable/tests/fixtures/page.json
trackable/tests/templates/tests/page_detail.html