Metadata-Version: 1.0
Name: django-trackable
Version: 0.3.8
Summary: A Django application which provides tools for out-of-band capture of arbitrary tracking data.
Home-page: http://github.com/yorkedork/django-trackable/tree/master
Author: Thom Linton
Author-email: thom.linton@gmail.com
License: BSD
Keywords: django tracking
Platform: UNKNOWN
Classifier: Development Status :: 3 - Alpha
Classifier: Environment :: Web Environment
Classifier: Framework :: Django
Classifier: Intended Audience :: Developers
Classifier: Programming Language :: Python
Classifier: Topic :: Software Development :: Libraries :: Python Modules
Classifier: License :: OSI Approved :: BSD License
